ecg_gudb_database.py
ecg_gudb_database-1.1.1.dist-info/LICENSE
ecg_gudb_database-1.1.1.dist-info/METADATA
ecg_gudb_database-1.1.1.dist-info/WHEEL
ecg_gudb_database-1.1.1.dist-info/top_level.txt
ecg_gudb_database-1.1.1.dist-info/RECORD
