Metadata-Version: 2.1
Name: ecg-gudb-database
Version: 1.1.1
Summary: API for a high precision ECG Database with annotated R peaks (GUDB)
Home-page: https://github.com/berndporr/ECG-GUDB
Author: Bernd Porr
Author-email: bernd.porr@glasgow.ac.uk
License: GPL 3.0
Classifier: Intended Audience :: Developers
Classifier: Operating System :: OS Independent
Classifier: Programming Language :: Python :: 3
License-File: LICENSE
Requires-Dist: numpy
Requires-Dist: requests
Requires-Dist: scipy
